{
	"name": "AzureSqlTable2",
	"properties": {
		"linkedServiceName": {
			"referenceName": "azuresql_ls_chaitanya_db",
			"type": "LinkedServiceReference"
		},
		"annotations": [],
		"type": "AzureSqlTable",
		"schema": [
			{
				"name": "SaleID",
				"type": "int",
				"precision": 10
			},
			{
				"name": "StoreID",
				"type": "int",
				"precision": 10
			},
			{
				"name": "Product",
				"type": "nvarchar"
			},
			{
				"name": "Quantity",
				"type": "int",
				"precision": 10
			},
			{
				"name": "UnitPrice",
				"type": "decimal",
				"precision": 10,
				"scale": 2
			},
			{
				"name": "SaleDate",
				"type": "datetime",
				"precision": 23,
				"scale": 3
			}
		],
		"typeProperties": {
			"schema": "dbo",
			"table": "Sales"
		}
	}
}